{"cameraMode":{"drawMode":0,"name":"Shaded","section":"Shading Mode"},"sceneLighting":true,"audioPlay":false,"sceneViewState":{"m_AlwaysRefresh":false,"showFog":true,"showSkybox":true,"showFlares":true,"showImageEffects":true,"showParticleSystems":true,"showVisualEffectGraphs":true,"m_FxEnabled":true},"in2DMode":false,"pivot":{"x":-15.441725730895996,"y":-18.65175437927246,"z":1.0436981916427613},"rotation":{"x":0.30068081617355349,"y":-0.6481578350067139,"z":0.3109442889690399,"w":0.6267446279525757},"size":16.87150764465332,"orthographic":false}